ifi_data_draft/__init__.py
ifi_data_draft/api.py
ifi_data_draft/exceptions.py
ifi_data_draft/metadata.py
ifi_data_draft/cli/__main__.py
ifi_data_draft/test/__init__.py
ifi_data_draft/test/create.py
ifi_data_draft/test/grafana.py
ifi_data_draft/test/insert.py
ifi_data_draft/test/live_test.py
ifi_data_draft/test/retrieve_data.py
ifi_data_draft/test/single_row.py
ifi_data_draft/test/test_config_api.py
ifi_data_draft/test/metadata/1.py
ifi_data_draft/test/metadata/2.py
ifi_data_draft/test/metadata/3.py
ifi_data_draft/test/metadata/4.py
ifi_data_draft/test/metadata/__init__.py
ifi_data_draft-0.1.0.dist-info/METADATA
ifi_data_draft-0.1.0.dist-info/WHEEL
ifi_data_draft-0.1.0.dist-info/top_level.txt
ifi_data_draft-0.1.0.dist-info/RECORD
