Metadata-Version: 2.4
Name: ifi_data_draft
Version: 0.1.0
Summary: Add your description here
Requires-Python: >=3.13
Requires-Dist: marimo>=0.13.6
Requires-Dist: pandas==2.2.1
Requires-Dist: polars>=1.29.0
Requires-Dist: psycopg2>=2.9.10
Requires-Dist: pytest>=8.4.0
Requires-Dist: python-dateutil==2.9.0
Requires-Dist: python-dotenv==0.21.0
Requires-Dist: requests>=2.32.3
Requires-Dist: ruff>=0.11.8
Requires-Dist: sqlalchemy==2.0.38
